{
  "id": "data",
  "title": "Data Preparation",
  "description": "Zarr-Cesium works best when datasets are prepared with web visualization constraints in mind:",
  "source": "@site/docs/data.md",
  "sourceDirName": ".",
  "slug": "/data",
  "permalink": "/zarr-cesium/docs/docs/data",
  "draft": false,
  "unlisted": false,
  "tags": [],
  "version": "current",
  "sidebarPosition": 6,
  "frontMatter": {
    "sidebar_position": 6,
    "title": "Data Preparation"
  },
  "sidebar": "tutorialSidebar",
  "previous": {
    "title": "ZarrCubeVelocityProvider",
    "permalink": "/zarr-cesium/docs/docs/providers/zarr-cube-velocity-provider"
  },
  "next": {
    "title": "API Reference",
    "permalink": "/zarr-cesium/docs/docs/api/"
  }
}